better_print/__init__.py
better_print/better_print.py
better_printer-0.0.2.dist-info/LICENSE
better_printer-0.0.2.dist-info/METADATA
better_printer-0.0.2.dist-info/WHEEL
better_printer-0.0.2.dist-info/top_level.txt
better_printer-0.0.2.dist-info/RECORD
